main.py
db_client/__init__.py
db_client/db.py
db_client/pool.py
mseep_mcp_server_tidb-0.1.4.dist-info/licenses/LICENSE
utils/logging.py
mseep_mcp_server_tidb-0.1.4.dist-info/METADATA
mseep_mcp_server_tidb-0.1.4.dist-info/WHEEL
mseep_mcp_server_tidb-0.1.4.dist-info/top_level.txt
mseep_mcp_server_tidb-0.1.4.dist-info/RECORD
