Metadata-Version: 2.4
Name: mseep-mcp-server-tidb
Version: 0.1.4
Summary: Add your description here
Author-email: mseep <support@skydeck.ai>
Requires-Python: >=3.13
License-File: LICENSE
Requires-Dist: mcp[cli]>=1.3.0
Requires-Dist: pydantic>=2.10.6
Requires-Dist: pymysql>=1.1.1
Requires-Dist: python-dotenv>=1.0.1
Dynamic: license-file
